browsing/__init__.py
browsing/apps.py
browsing/filters.py
browsing/forms.py
browsing/tests.py
browsing/urls.py
browsing/utils.py
browsing/views.py
browsing/static/browsing/js/filter-for-blank-fields.js
browsing/static/browsing/js/set-form-attributes.js
browsing/templates/browsing/generic_create.html
browsing/templates/browsing/generic_detail.html
browsing/templates/browsing/generic_list.html
browsing/templates/browsing/partials/column_selector.html
browsing/templates/browsing/partials/create-edit_breadcrumb.html
browsing/templates/browsing/partials/detailview_breadcrumb.html
browsing/templates/browsing/partials/detailview_title.html
browsing/templates/browsing/partials/download_menu.html
browsing/templates/browsing/partials/listview_breadcrumb.html
browsing/templates/browsing/partials/pagination.html
browsing/templates/browsing/partials/table.html
acdh_django_browsing-3.2.dist-info/LICENSE.txt
acdh_django_browsing-3.2.dist-info/METADATA
acdh_django_browsing-3.2.dist-info/WHEEL
acdh_django_browsing-3.2.dist-info/top_level.txt
acdh_django_browsing-3.2.dist-info/RECORD
