Metadata-Version: 2.2
Name: acdh-django-browsing
Version: 3.2
Summary: Django-App providing some useful things to create browsing views
Author-email: Peter Andorfer <peter.andorfer@oeaw.ac.at>
Project-URL: Homepage, https://github.com/acdh-oeaw/acdh-django-browsing
Keywords: django
Requires-Python: >=3.10
License-File: LICENSE.txt
Requires-Dist: crispy-bootstrap5
Requires-Dist: django-crispy-forms
Requires-Dist: django-filter
Requires-Dist: django-super-deduper
Requires-Dist: django-tables2
Requires-Dist: tablib
Provides-Extra: tests
Requires-Dist: pytest; extra == "tests"
Requires-Dist: coverage; extra == "tests"
Provides-Extra: linting
Requires-Dist: flake8; extra == "linting"
Provides-Extra: build
Requires-Dist: build; extra == "build"
